[
  {
    "id": "mizunoatu",
    "name": "水野あつ",
    "nameKana": "みずのあつ",
    "aliases": [],
    "activeYears": "2018-",
    "summary": "繊細で透明感のあるメロディと心情を丁寧に描く歌詞が特徴のボカロP。",
    "links": {
      "youtube": "https://www.youtube.com/@atsu361",
      "x": "https://x.com/atsu361",
      "website": ""
    }
  },
  {
    "id": "kurousap",
    "name": "黒うさP",
    "nameKana": "くろうさぴー",
    "aliases": ["WhiteFlame"],
    "activeYears": "2008-",
    "summary": "和風テイストと物語性の強い歌詞で知られるボカロP。",
    "links": {
      "youtube": "https://www.youtube.com/@WhiteFlameOfficial",
      "x": "https://x.com/whiteflame_info",
      "website": ""
    }
  },
  {
    "id": "deco27",
    "name": "DECO*27",
    "nameKana": "でこにーな",
    "aliases": [],
    "activeYears": "2008-",
    "summary": "キャッチーで中毒性のあるメロディと現代的なポップサウンドが特徴のボカロP。",
    "links": {
      "youtube": "http://www.youtube.com/@DECO27",
      "x": "https://x.com/deco27",
      "website": "https://otoiro.co.jp/creator/deco27"
    }
  },
  {
    "id": "kz",
    "name": "kz",
    "nameKana": "",
    "aliases": ["livetune"],
    "activeYears": "2007-",
    "summary": "透明感のあるエレクトロサウンドと洗練されたメロディが特徴のボカロP。",
    "links": {
      "youtube": "http://www.youtube.com/@kzlivetune",
      "x": "https://x.com/kz_lt",
      "website": ""
    }
  },
  {
    "id": "ryo",
    "name": "ryo",
    "nameKana": "りょう",
    "aliases": ["supercell"],
    "activeYears": "2007-",
    "summary": "壮大でエモーショナルなメロディと物語性の強い歌詞が特徴のボカロP。",
    "links": {
      "youtube": "http://www.youtube.com/@spclryo2673",
      "x": "https://x.com/ryo_spcl",
      "website": "https://www.ryo-supercell.com"
    }
  },
  {
    "id": "mikitop",
    "name": "みきとP",
    "nameKana": "",
    "aliases": [],
    "activeYears": "",
    "summary": "",
    "links": {
      "youtube": "",
      "x": "",
      "website": ""
    }
  },
  {
    "id": "hati",
    "name": "ハチ",
    "nameKana": "",
    "aliases": [],
    "activeYears": "",
    "summary": "",
    "links": {
      "youtube": "",
      "x": "",
      "website": ""
    }
  },
  {
    "id": "reruriri",
    "name": "れるりり",
    "nameKana": "",
    "aliases": [],
    "activeYears": "",
    "summary": "",
    "links": {
      "youtube": "",
      "x": "",
      "website": ""
    }
  },
  {
    "id": "164",
    "name": "164",
    "nameKana": "",
    "aliases": [],
    "activeYears": "",
    "summary": "",
    "links": {
      "youtube": "",
      "x": "",
      "website": ""
    }
  },
  {
    "id": "kemu",
    "name": "kemu",
    "nameKana": "",
    "aliases": [],
    "activeYears": "",
    "summary": "",
    "links": {
      "youtube": "",
      "x": "",
      "website": ""
    }
  },
  {
    "id": "zin",
    "name": "じん",
    "nameKana": "",
    "aliases": [],
    "activeYears": "",
    "summary": "",
    "links": {
      "youtube": "",
      "x": "",
      "website": ""
    }
  },
  {
    "id": "orangestar",
    "name": "Orangestar",
    "nameKana": "",
    "aliases": [],
    "activeYears": "",
    "summary": "",
    "links": {
      "youtube": "",
      "x": "",
      "website": ""
    }
  },
  {
    "id": "barun",
    "name": "バルーン",
    "nameKana": "",
    "aliases": [],
    "activeYears": "",
    "summary": "",
    "links": {
      "youtube": "",
      "x": "",
      "website": ""
    }
  },
  {
    "id": "kanzakiiori",
    "name": "カンザキイオリ",
    "nameKana": "",
    "aliases": [],
    "activeYears": "",
    "summary": "",
    "links": {
      "youtube": "",
      "x": "",
      "website": ""
    }
  },
  {
    "id": "kanaria",
    "name": "Kanaria",
    "nameKana": "",
    "aliases": [],
    "activeYears": "",
    "summary": "",
    "links": {
      "youtube": "",
      "x": "",
      "website": ""
    }
  },
  {
    "id": "surii",
    "name": "すりぃ",
    "nameKana": "",
    "aliases": [],
    "activeYears": "",
    "summary": "",
    "links": {
      "youtube": "",
      "x": "",
      "website": ""
    }
  },
  {
    "id": "teniwoha",
    "name": "てにをは",
    "nameKana": "",
    "aliases": [],
    "activeYears": "",
    "summary": "",
    "links": {
      "youtube": "",
      "x": "",
      "website": ""
    }
  },
  {
    "id": "kairikibea",
    "name": "かいりきベア",
    "nameKana": "",
    "aliases": [],
    "activeYears": "",
    "summary": "",
    "links": {
      "youtube": "",
      "x": "",
      "website": ""
    }
  },
  {
    "id": "chinozo",
    "name": "Chinozo",
    "nameKana": "",
    "aliases": [],
    "activeYears": "",
    "summary": "",
    "links": {
      "youtube": "",
      "x": "",
      "website": ""
    }
  },
  {
    "id": "tumiki",
    "name": "ツミキ",
    "nameKana": "",
    "aliases": [],
    "activeYears": "",
    "summary": "",
    "links": {
      "youtube": "",
      "x": "",
      "website": ""
    }
  },
  {
    "id": "pinokiopi",
    "name": "ピノキオピー",
    "nameKana": "",
    "aliases": [],
    "activeYears": "",
    "summary": "",
    "links": {
      "youtube": "",
      "x": "",
      "website": ""
    }
  },
  {
    "id": "iroha",
    "name": "iroha",
    "nameKana": "",
    "aliases": [],
    "activeYears": "",
    "summary": "",
    "links": {
      "youtube": "",
      "x": "",
      "website": ""
    }
  },
  {
    "id": "noripi",
    "name": "のりぴー",
    "nameKana": "",
    "aliases": [],
    "activeYears": "",
    "summary": "",
    "links": {
      "youtube": "",
      "x": "",
      "website": ""
    }
  },
  {
    "id": "40mp",
    "name": "40mP",
    "nameKana": "",
    "aliases": [],
    "activeYears": "",
    "summary": "",
    "links": {
      "youtube": "",
      "x": "",
      "website": ""
    }
  },
  {
    "id": "tyoutyop",
    "name": "蝶々P",
    "nameKana": "",
    "aliases": [],
    "activeYears": "",
    "summary": "",
    "links": {
      "youtube": "",
      "x": "",
      "website": ""
    }
  },
  {
    "id": "dixieflatline",
    "name": "Dixie Flatline",
    "nameKana": "",
    "aliases": [],
    "activeYears": "",
    "summary": "",
    "links": {
      "youtube": "",
      "x": "",
      "website": ""
    }
  },
  {
    "id": "yuuyu",
    "name": "ゆうゆ",
    "nameKana": "",
    "aliases": [],
    "activeYears": "",
    "summary": "",
    "links": {
      "youtube": "",
      "x": "",
      "website": ""
    }
  },
  {
    "id": "zimisamu",
    "name": "ジミーサムP",
    "nameKana": "",
    "aliases": [],
    "activeYears": "",
    "summary": "",
    "links": {
      "youtube": "",
      "x": "",
      "website": ""
    }
  },
  {
    "id": "keeno",
    "name": "keeno",
    "nameKana": "",
    "aliases": [],
    "activeYears": "",
    "summary": "",
    "links": {
      "youtube": "",
      "x": "",
      "website": ""
    }
  },
  {
    "id": "nanou",
    "name": "ナノウ",
    "nameKana": "",
    "aliases": [],
    "activeYears": "",
    "summary": "",
    "links": {
      "youtube": "",
      "x": "",
      "website": ""
    }
  },
  {
    "id": "wowaka",
    "name": "wowaka",
    "nameKana": "",
    "aliases": [],
    "activeYears": "",
    "summary": "",
    "links": {
      "youtube": "",
      "x": "",
      "website": ""
    }
  },
  {
    "id": "junky",
    "name": "Junky",
    "nameKana": "",
    "aliases": [],
    "activeYears": "",
    "summary": "",
    "links": {
      "youtube": "",
      "x": "",
      "website": ""
    }
  },
  {
    "id": "koyori",
    "name": "koyori",
    "nameKana": "",
    "aliases": [],
    "activeYears": "",
    "summary": "",
    "links": {
      "youtube": "",
      "x": "",
      "website": ""
    }
  },
  {
    "id": "neru",
    "name": "Neru",
    "nameKana": "",
    "aliases": [],
    "activeYears": "",
    "summary": "",
    "links": {
      "youtube": "",
      "x": "",
      "website": ""
    }
  },
  {
    "id": "mothy",
    "name": "mothy",
    "nameKana": "",
    "aliases": [],
    "activeYears": "",
    "summary": "",
    "links": {
      "youtube": "",
      "x": "",
      "website": ""
    }
  },
  {
    "id": "yanagi",
    "name": "yanagi",
    "nameKana": "",
    "aliases": [],
    "activeYears": "",
    "summary": "",
    "links": {
      "youtube": "",
      "x": "",
      "website": ""
    }
  },
  {
    "id": "minato",
    "name": "minato",
    "nameKana": "",
    "aliases": [],
    "activeYears": "",
    "summary": "",
    "links": {
      "youtube": "",
      "x": "",
      "website": ""
    }
  },
  {
    "id": "doriko",
    "name": "doriko",
    "nameKana": "",
    "aliases": [],
    "activeYears": "",
    "summary": "",
    "links": {
      "youtube": "",
      "x": "",
      "website": ""
    }
  },
  {
    "id": "t-pocket",
    "name": "T-POCKET",
    "nameKana": "",
    "aliases": [],
    "activeYears": "",
    "summary": "",
    "links": {
      "youtube": "",
      "x": "",
      "website": ""
    }
  },
  {
    "id": "halyosy",
    "name": "halyosy",
    "nameKana": "",
    "aliases": [],
    "activeYears": "",
    "summary": "",
    "links": {
      "youtube": "",
      "x": "",
      "website": ""
    }
  },
  {
    "id": "hinadenkou",
    "name": "日向電工",
    "nameKana": "",
    "aliases": [],
    "activeYears": "",
    "summary": "",
    "links": {
      "youtube": "",
      "x": "",
      "website": ""
    }
  },
  {
    "id": "n-buna",
    "name": "n-buna",
    "nameKana": "",
    "aliases": [],
    "activeYears": "",
    "summary": "",
    "links": {
      "youtube": "",
      "x": "",
      "website": ""
    }
  },
  {
    "id": "sukoppu",
    "name": "すこっぷ",
    "nameKana": "",
    "aliases": [],
    "activeYears": "",
    "summary": "",
    "links": {
      "youtube": "",
      "x": "",
      "website": ""
    }
  },
  {
    "id": "hiiragikirai",
    "name": "柊キライ",
    "nameKana": "",
    "aliases": [],
    "activeYears": "",
    "summary": "",
    "links": {
      "youtube": "",
      "x": "",
      "website": ""
    }
  },
  {
    "id": "yuriikanon",
    "name": "ユリイ・カノン",
    "nameKana": "",
    "aliases": [],
    "activeYears": "",
    "summary": "",
    "links": {
      "youtube": "",
      "x": "",
      "website": ""
    }
  },
  {
    "id": "nayutanseizin",
    "name": "ナユタン星人",
    "nameKana": "",
    "aliases": [],
    "activeYears": "",
    "summary": "",
    "links": {
      "youtube": "",
      "x": "",
      "website": ""
    }
  },
  {
    "id": "syudou",
    "name": "syudou",
    "nameKana": "",
    "aliases": [],
    "activeYears": "",
    "summary": "",
    "links": {
      "youtube": "",
      "x": "",
      "website": ""
    }
  },
  {
    "id": "nuyuri",
    "name": "ぬゆり",
    "nameKana": "",
    "aliases": [],
    "activeYears": "",
    "summary": "",
    "links": {
      "youtube": "",
      "x": "",
      "website": ""
    }
  },
  {
    "id": "eve",
    "name": "Eve",
    "nameKana": "",
    "aliases": [],
    "activeYears": "",
    "summary": "",
    "links": {
      "youtube": "",
      "x": "",
      "website": ""
    }
  },
  {
    "id": "tokotoko",
    "name": "TOKOTOKO",
    "nameKana": "",
    "aliases": [],
    "activeYears": "",
    "summary": "",
    "links": {
      "youtube": "",
      "x": "",
      "website": ""
    }
  },
  {
    "id": "easypop",
    "name": "EasyPop",
    "nameKana": "",
    "aliases": [],
    "activeYears": "",
    "summary": "",
    "links": {
      "youtube": "",
      "x": "",
      "website": ""
    }
  },
  {
    "id": "zizasu",
    "name": "じーざす",
    "nameKana": "",
    "aliases": [],
    "activeYears": "",
    "summary": "",
    "links": {
      "youtube": "",
      "x": "",
      "website": ""
    }
  },
  {
    "id": "ginsaku",
    "name": "銀サク",
    "nameKana": "",
    "aliases": [],
    "activeYears": "",
    "summary": "",
    "links": {
      "youtube": "",
      "x": "",
      "website": ""
    }
  },
  {
    "id": "rokuro",
    "name": "ろくろ",
    "nameKana": "",
    "aliases": [],
    "activeYears": "",
    "summary": "",
    "links": {
      "youtube": "",
      "x": "",
      "website": ""
    }
  },
  {
    "id": "19ssoundfactory",
    "name": "19’s Sound Factory",
    "nameKana": "",
    "aliases": [],
    "activeYears": "",
    "summary": "",
    "links": {
      "youtube": "",
      "x": "",
      "website": ""
    }
  },
  {
    "id": "hurukawahonpo",
    "name": "古川本舗",
    "nameKana": "",
    "aliases": [],
    "activeYears": "",
    "summary": "",
    "links": {
      "youtube": "",
      "x": "",
      "website": ""
    }
  },
  {
    "id": "nem",
    "name": "Nem",
    "nameKana": "",
    "aliases": [],
    "activeYears": "",
    "summary": "",
    "links": {
      "youtube": "",
      "x": "",
      "website": ""
    }
  },
  {
    "id": "azari",
    "name": "Azari",
    "nameKana": "",
    "aliases": [],
    "activeYears": "",
    "summary": "",
    "links": {
      "youtube": "",
      "x": "",
      "website": ""
    }
  },
  {
    "id": "iyowa",
    "name": "いよわ",
    "nameKana": "",
    "aliases": [],
    "activeYears": "",
    "summary": "",
    "links": {
      "youtube": "",
      "x": "",
      "website": ""
    }
  },
  {
    "id": "inabakumori",
    "name": "稲葉曇",
    "nameKana": "",
    "aliases": [],
    "activeYears": "",
    "summary": "",
    "links": {
      "youtube": "",
      "x": "",
      "website": ""
    }
  },
  {
    "id": "nirukazitu",
    "name": "煮ル果実",
    "nameKana": "",
    "aliases": [],
    "activeYears": "",
    "summary": "",
    "links": {
      "youtube": "",
      "x": "",
      "website": ""
    }
  },
  {
    "id": "maretu",
    "name": "Maretu",
    "nameKana": "",
    "aliases": [],
    "activeYears": "",
    "summary": "",
    "links": {
      "youtube": "",
      "x": "",
      "website": ""
    }
  },
  {
    "id": "wadatakeaki",
    "name": "和田たけあき",
    "nameKana": "",
    "aliases": [],
    "activeYears": "",
    "summary": "",
    "links": {
      "youtube": "",
      "x": "",
      "website": ""
    }
  },
  {
    "id": "hitosizukuyama",
    "name": "ひとしずく×やま△",
    "nameKana": "",
    "aliases": [],
    "activeYears": "",
    "summary": "",
    "links": {
      "youtube": "",
      "x": "",
      "website": ""
    }
  },
  {
    "id": "tanakab",
    "name": "田中B",
    "nameKana": "",
    "aliases": [],
    "activeYears": "",
    "summary": "",
    "links": {
      "youtube": "",
      "x": "",
      "website": ""
    }
  },
  {
    "id": "kuwagatap",
    "name": "クワガタP",
    "nameKana": "",
    "aliases": [],
    "activeYears": "",
    "summary": "",
    "links": {
      "youtube": "",
      "x": "",
      "website": ""
    }
  },
  {
    "id": "niop",
    "name": "におP",
    "nameKana": "",
    "aliases": [],
    "activeYears": "",
    "summary": "",
    "links": {
      "youtube": "",
      "x": "",
      "website": ""
    }
  },
  {
    "id": "noboru",
    "name": "のぼる↑",
    "nameKana": "",
    "aliases": [],
    "activeYears": "",
    "summary": "",
    "links": {
      "youtube": "",
      "x": "",
      "website": ""
    }
  },
  {
    "id": "yuyoyuppe",
    "name": "ゆよゆっぺ",
    "nameKana": "",
    "aliases": [],
    "activeYears": "",
    "summary": "",
    "links": {
      "youtube": "",
      "x": "",
      "website": ""
    }
  },
  {
    "id": "yutyap",
    "name": "ゆちゃP",
    "nameKana": "",
    "aliases": [],
    "activeYears": "",
    "summary": "",
    "links": {
      "youtube": "",
      "x": "",
      "website": ""
    }
  },
  {
    "id": "buzzg",
    "name": "buzzG",
    "nameKana": "",
    "aliases": [],
    "activeYears": "",
    "summary": "",
    "links": {
      "youtube": "",
      "x": "",
      "website": ""
    }
  },
  {
    "id": "supercell",
    "name": "supercell",
    "nameKana": "",
    "aliases": [],
    "activeYears": "",
    "summary": "",
    "links": {
      "youtube": "",
      "x": "",
      "website": ""
    }
  },
  {
    "id": "suzumu",
    "name": "スズム",
    "nameKana": "",
    "aliases": [],
    "activeYears": "",
    "summary": "",
    "links": {
      "youtube": "",
      "x": "",
      "website": ""
    }
  },
  {
    "id": "sasakureuk",
    "name": "sasakure.UK",
    "nameKana": "",
    "aliases": [],
    "activeYears": "",
    "summary": "",
    "links": {
      "youtube": "",
      "x": "",
      "website": ""
    }
  },
  {
    "id": "mitchiem",
    "name": "Mitchie M",
    "nameKana": "",
    "aliases": [],
    "activeYears": "",
    "summary": "",
    "links": {
      "youtube": "",
      "x": "",
      "website": ""
    }
  },
  {
    "id": "kinosita",
    "name": "キノシタ",
    "nameKana": "",
    "aliases": [],
    "activeYears": "",
    "summary": "",
    "links": {
      "youtube": "",
      "x": "",
      "website": ""
    }
  },
  {
    "id": "harryp",
    "name": "HarryP",
    "nameKana": "",
    "aliases": [],
    "activeYears": "",
    "summary": "",
    "links": {
      "youtube": "",
      "x": "",
      "website": ""
    }
  },
  {
    "id": "cosmobousoup",
    "name": "cosMo@暴走P",
    "nameKana": "",
    "aliases": [],
    "activeYears": "",
    "summary": "",
    "links": {
      "youtube": "",
      "x": "",
      "website": ""
    }
  },
  {
    "id": "isikawatiaki",
    "name": "石川智晶P",
    "nameKana": "",
    "aliases": [],
    "activeYears": "",
    "summary": "",
    "links": {
      "youtube": "",
      "x": "",
      "website": ""
    }
  },
  {
    "id": "owatap",
    "name": "オワタP",
    "nameKana": "",
    "aliases": [],
    "activeYears": "",
    "summary": "",
    "links": {
      "youtube": "",
      "x": "",
      "website": ""
    }
  },
  {
    "id": "agoaniki",
    "name": "アゴアニキ",
    "nameKana": "",
    "aliases": [],
    "activeYears": "",
    "summary": "",
    "links": {
      "youtube": "",
      "x": "",
      "website": ""
    }
  },
  {
    "id": "zyon",
    "name": "じょん",
    "nameKana": "",
    "aliases": [],
    "activeYears": "",
    "summary": "",
    "links": {
      "youtube": "",
      "x": "",
      "website": ""
    }
  },
  {
    "id": "osterproject",
    "name": "OSTER project",
    "nameKana": "",
    "aliases": [],
    "activeYears": "",
    "summary": "",
    "links": {
      "youtube": "",
      "x": "",
      "website": ""
    }
  },
  {
    "id": "toraboruta",
    "name": "トラボルタ",
    "nameKana": "",
    "aliases": [],
    "activeYears": "",
    "summary": "",
    "links": {
      "youtube": "",
      "x": "",
      "website": ""
    }
  },
  {
    "id": "sigunarup",
    "name": "シグナルP",
    "nameKana": "",
    "aliases": [],
    "activeYears": "",
    "summary": "",
    "links": {
      "youtube": "",
      "x": "",
      "website": ""
    }
  },
  {
    "id": "tokup",
    "name": "とくP",
    "nameKana": "",
    "aliases": [],
    "activeYears": "",
    "summary": "",
    "links": {
      "youtube": "",
      "x": "",
      "website": ""
    }
  },
  {
    "id": "divela",
    "name": "DIVELA",
    "nameKana": "",
    "aliases": [],
    "activeYears": "",
    "summary": "",
    "links": {
      "youtube": "",
      "x": "",
      "website": ""
    }
  }
]
